toybox/__init__.py
toybox/langhelpers.py
toybox/shortcuts.py
toybox/simple/__init__.py
toybox/simple/simpleviews.py
toybox/simpleapi/__init__.py
toybox/simpleapi/jsonresponse.py
toybox/swagger/__init__.py
toybox/swagger/decorator.py
toybox/swagger/renderers.py
toybox-0.0.2.dist-info/DESCRIPTION.rst
toybox-0.0.2.dist-info/entry_points.txt
toybox-0.0.2.dist-info/METADATA
toybox-0.0.2.dist-info/metadata.json
toybox-0.0.2.dist-info/RECORD
toybox-0.0.2.dist-info/top_level.txt
toybox-0.0.2.dist-info/WHEEL
