Metadata-Version: 2.0
Name: toybox
Version: 0.0.2
Summary: tiny api framework. don't use this in production.
Home-page: https://github.com/podhmo/toybox
Author: podhmo
Author-email: ababjam61@gmail.com
License: UNKNOWN
Keywords: web,onefile,pyramid
Platform: UNKNOWN
Classifier: Programming Language :: Python
Classifier: Programming Language :: Python :: Implementation :: CPython
Requires-Dist: pyramid
Provides-Extra: docs
Provides-Extra: swagger
Requires-Dist: swagger-marshmallow-codegen; extra == 'swagger'
Requires-Dist: pyramid-swagger-router; extra == 'swagger'
Provides-Extra: testing
